README.txt
setup.py
watchntouch.py
watchntouch.egg-info/PKG-INFO
watchntouch.egg-info/SOURCES.txt
watchntouch.egg-info/dependency_links.txt
watchntouch.egg-info/entry_points.txt
watchntouch.egg-info/requires.txt
watchntouch.egg-info/top_level.txt