Metadata-Version: 1.1
Name: watchntouch
Version: 1.0
Summary: Poll a directory for changes and re-touch changed paths so that inotify- incapable mounts (like CIFS) receive inotify events anyway.
Home-page: https://github.com/rubyruy/watchntouch
Author: Ruy Asan
Author-email: ruyasan@gmail.com
License: UNKNOWN
Platform: UNKNOWN
Classifier: Programming Language :: Python
Classifier: Programming Language :: Python :: 2
Classifier: Programming Language :: Python :: 2.6
Classifier: Programming Language :: Python :: 2.7
Classifier: License :: OSI Approved :: BSD License
Classifier: Environment :: Console
Classifier: Operating System :: POSIX
Classifier: Operating System :: MacOS :: MacOS X
